tekleo_services_client/__init__.py
tekleo_services_client/client_ai_car_plate.py
tekleo_services_client-0.0.0.1.dist-info/LICENSE.txt
tekleo_services_client-0.0.0.1.dist-info/METADATA
tekleo_services_client-0.0.0.1.dist-info/WHEEL
tekleo_services_client-0.0.0.1.dist-info/top_level.txt
tekleo_services_client-0.0.0.1.dist-info/RECORD
