Metadata-Version: 2.1
Name: tekleo-services-client
Version: 0.0.0.1
Summary: UNKNOWN
Home-page: https://github.com/jpleorx/tekleo-services-client
Author: Leo Ertuna
Author-email: leo.ertuna@gmail.com
License: Creative Commons Attribution-NonCommercial-NoDerivatives 4.0 International Public License
Download-URL: https://pypi.org/project/tekleo-services-client/
Platform: UNKNOWN
Requires-Dist: tekleo-common-message-protocol
Requires-Dist: tekleo-common-utils
